{"Apple ceder apple rust": 0, "Apple scab": 1, "Grape esca": 2, "apple black rot": 3, "apple healthy": 4, "background without leaves": 5, "blueberry healthy": 6, "cherry healthy": 7, "cherry powdery mildew": 8, "corn cercospora leaf": 9, "corn common rust": 10, "corn healthy": 11, "corn northen leaf blight": 12, "grape black rot": 13, "grape healthy": 14, "grape leaf blight": 15, "orange haunglongbing": 16, "peach bacterial spot": 17, "peach healthy": 18, "pepper bacterial spot": 19, "pepper bell healthy": 20, "potato early blight": 21, "potato healthy": 22, "potato late blight": 23, "raspberry healthy": 24, "soyaben healthy": 25, "squash powdery mildew": 26, "starwberry healthy": 27, "starwberry leaf scorch": 28, "tomato bacterial spot": 29, "tomato early blight": 30, "tomato healthy": 31, "tomato late blight": 32, "tomato leaf mold": 33, "tomato mosaic virus": 34, "tomato septoria leaf spot": 35, "tomato spider mites two spotted spider mites": 36, "tomato target spot": 37, "tomato yellow leaf curl virus": 38, "tomato-bacterial-spot": 39, "tomato-leaf-curl-virus": 40, "tomato-mold": 41}